{
  "_id": "be9hXz6idWXlVS0Z",
  "name": "Rime-Blooded",
  "type": "feat",
  "img": "systems/pf1/icons/spells/fireball-red-3.jpg",
  "data": {
    "description": {
      "value": "<strong>Sorcerer Wildblooded Bloodline</strong><br/><br/><p>The wintry origin of your magic flows like ice water in your veins.</p><p><b>Associated Bloodline: </b>Boreal.</p><p><b>Bloodline Arcana: </b>Whenever you cast a spell with the cold descriptor, you may select one target of the spell to be slowed (as the spell) for 1 round. A Fortitude save (DC 10 + the level of cold spell + your Charisma modifier) negates the effect.</p><p><b>Bloodline Powers: </b>Sometimes you must bring the cold to your enemies.</p>",
      "chat": "",
      "unidentified": ""
    },
    "tags": [
      [
        [
          "Sorcerer"
        ],
        [
          "Sorcerer Wildblooded Bloodline"
        ]
      ]
    ],
    "actions": [],
    "uses": {
      "per": null,
      "value": 0,
      "maxFormula": "",
      "autoDeductCharges": true,
      "autoDeductChargesCost": "1"
    },
    "attackNotes": [],
    "effectNotes": [],
    "changes": [],
    "changeFlags": {
      "loseDexToAC": false,
      "noEncumbrance": false,
      "mediumArmorFullSpeed": false,
      "heavyArmorFullSpeed": false
    },
    "contextNotes": [],
    "links": {
      "children": [],
      "charges": []
    },
    "tag": "",
    "useCustomTag": false,
    "armorProf": {
      "value": [],
      "custom": ""
    },
    "weaponProf": {
      "value": [],
      "custom": ""
    },
    "languages": {
      "value": [],
      "custom": ""
    },
    "flags": {
      "boolean": {},
      "dictionary": {}
    },
    "scriptCalls": [],
    "featType": "classFeat",
    "associations": {
      "classes": [
        [
          "Sorcerer"
        ]
      ]
    },
    "showInQuickbar": false,
    "nonlethal": false,
    "abilityType": "none",
    "crOffset": "",
    "disabled": false,
    "classSkills": {},
    "activation": {
      "cost": 1,
      "type": ""
    },
    "unchainedAction": {
      "activation": {
        "cost": 1,
        "type": ""
      }
    },
    "duration": {
      "value": null,
      "units": ""
    },
    "actionType": null,
    "ability": {
      "damageMult": 1,
      "critMult": 2
    },
    "size": "med",
    "range": {
      "maxIncrements": 1
    }
  },
  "effects": [],
  "folder": null,
  "sort": 0,
  "permission": {
    "default": 0
  },
  "flags": {}
}
