{
  "_id": "oi1XCTPA0MjMDjY6",
  "name": "Verdant Vine",
  "type": "equipment",
  "img": "icons/svg/item-bag.svg",
  "data": {
    "description": {
      "value": "<h2></b>Description</b></h2></p><p>Consisting of a vine with five green berries, a verdant vine is worn tied around the wrist. Once per day on command, the wearer can pinch a berry off the vine, and throw it up to 30 feet away, like a splash weapon. Viciously thorny vines erupt in a 20-foot radius from the point of impact, even if the berry misses its target. Creatures within the area must succeed at a DC 16 Reflex saving throw or become entangled, as the spell entangle, as the vines coil around the creature's legs. The vines persist, but at the start of the affected creature's turn, it gains a new saving throw against the effect. If the affected creature fails the saving throw, it also takes 1d4 points of damage.   A DC 20 Strength check, made as a standard action, allows an affected creature to break free and end the effect. Failing the check causes the vines to constrict, dealing 1d4 points of damage.<br><p><b>Base Item:</b> </p><h3><b>Requirements</b></h3><p>Craft Wondrous Item, entangle, plant growth</p><h3><b>Source: </b></h3>Ultimate Equipment",
      "chat": "",
      "unidentified": ""
    },
    "tags": [],
    "quantity": 1,
    "weight": 0,
    "price": 6000,
    "size": "med",
    "equipped": true,
    "resizing": false,
    "identified": true,
    "hp": {
      "max": 10,
      "value": 10
    },
    "broken": false,
    "hardness": 0,
    "carried": true,
    "unidentified": {
      "price": 0,
      "name": ""
    },
    "identifiedName": "Verdant Vine",
    "cl": 5,
    "aura": {
      "custom": true,
      "school": "conjuration"
    },
    "activation": {
      "cost": 1,
      "type": ""
    },
    "unchainedAction": {
      "activation": {
        "cost": 1,
        "type": ""
      }
    },
    "duration": {
      "value": null,
      "units": ""
    },
    "target": {
      "value": ""
    },
    "range": {
      "value": null,
      "units": "",
      "maxIncrements": 1,
      "minValue": null,
      "minUnits": ""
    },
    "uses": {
      "value": 0,
      "per": null,
      "autoDeductCharges": true,
      "autoDeductChargesCost": "1",
      "maxFormula": "",
      "max": 0
    },
    "changes": [],
    "changeFlags": {
      "loseDexToAC": false,
      "noEncumbrance": false,
      "mediumArmorFullSpeed": false,
      "heavyArmorFullSpeed": false,
      "noStr": false,
      "noDex": false,
      "oneInt": false,
      "oneWis": false,
      "oneCha": false
    },
    "contextNotes": [],
    "measureTemplate": {
      "type": "",
      "size": "",
      "overrideColor": false,
      "customColor": "",
      "overrideTexture": false,
      "customTexture": ""
    },
    "attackName": "",
    "actionType": null,
    "attackBonus": "",
    "critConfirmBonus": "",
    "damage": {
      "parts": [],
      "critParts": [],
      "nonCritParts": []
    },
    "attackParts": [],
    "formulaicAttacks": {
      "count": {
        "formula": ""
      },
      "bonus": {
        "formula": ""
      },
      "label": null
    },
    "formula": "",
    "ability": {
      "attack": null,
      "damage": null,
      "damageMult": 1,
      "critRange": 20,
      "critMult": 2
    },
    "save": {
      "dc": 0,
      "type": "",
      "description": ""
    },
    "effectNotes": [],
    "attackNotes": [],
    "soundEffect": "",
    "links": {
      "children": [],
      "charges": []
    },
    "tag": "verdantVine",
    "useCustomTag": false,
    "flags": {
      "boolean": [],
      "dictionary": []
    },
    "scriptCalls": [],
    "masterwork": false,
    "enh": null,
    "attackType": "weapon",
    "nonlethal": false,
    "proficient": true,
    "primaryAttack": true,
    "held": "normal",
    "equipmentType": "misc",
    "equipmentSubtype": "wondrous",
    "armor": {
      "value": 0,
      "dex": null,
      "acp": 0,
      "enh": 0
    },
    "spellFailure": 0,
    "slot": "wrists"
  },
  "effects": [],
  "folder": null,
  "sort": 0,
  "permission": {
    "default": 0,
    "T7ruBbHuMiFYUDxv": 3
  },
  "flags": {}
}
