{
  "_id": "C93Box1Oy2Fllwhe",
  "name": "Body Shield",
  "type": "feat",
  "img": "systems/pf1/icons/skills/yellow_18.jpg",
  "system": {
    "description": {
      "value": "<p><em>With a sly maneuver, you force a grappled opponent into the path of an incoming attack.</em><br /><br /><strong>Prerequisites</strong><br />Dex 13, Improved Grapple, Improved Unarmed Strike, base attack bonus +6.<br /><br /><strong>Benefit</strong><br />As an immediate action while you are grappling an adjacent creature, you can make a grapple combat maneuver check against that creature to gain cover against a single attack. If you are successful and the attack misses you, that attack targets the creature you used as cover, using the same attack roll. You cannot use this feat against a creature grappling you, and the cover you gain ends after the attack you gained cover against is resolved.<br /><br /></p>\n<p><strong>Combat Trick<br /></strong>You can spend 5 stamina points to use this feat against a creature grappling you.</p>",
      "chat": "",
      "unidentified": ""
    },
    "tags": [
      [
        "PFS"
      ],
      [
        "Combat"
      ]
    ],
    "actions": [],
    "uses": {
      "per": null,
      "value": 0,
      "maxFormula": "",
      "autoDeductCharges": true,
      "autoDeductChargesCost": "1"
    },
    "attackNotes": [],
    "effectNotes": [],
    "changes": [],
    "changeFlags": {
      "loseDexToAC": false,
      "noEncumbrance": false,
      "mediumArmorFullSpeed": false,
      "heavyArmorFullSpeed": false
    },
    "contextNotes": [],
    "links": {
      "children": [],
      "charges": []
    },
    "tag": "",
    "useCustomTag": false,
    "armorProf": {
      "value": [],
      "custom": ""
    },
    "weaponProf": {
      "value": [],
      "custom": ""
    },
    "languages": {
      "value": [],
      "custom": ""
    },
    "flags": {
      "boolean": {},
      "dictionary": {}
    },
    "scriptCalls": [],
    "featType": "feat",
    "associations": {
      "classes": []
    },
    "showInQuickbar": false,
    "abilityType": "none",
    "crOffset": "",
    "disabled": false,
    "classSkills": {},
    "activation": {
      "cost": 1,
      "type": ""
    },
    "unchainedAction": {
      "activation": {
        "cost": 1,
        "type": ""
      }
    },
    "duration": {
      "value": null,
      "units": ""
    },
    "ability": {
      "damageMult": 1,
      "critMult": 2
    },
    "attack": {},
    "size": "med",
    "range": {
      "maxIncrements": 1
    }
  },
  "effects": [],
  "folder": null,
  "sort": 0,
  "ownership": {
    "default": 0
  },
  "flags": {},
  "_stats": {
    "systemId": "pf1",
    "systemVersion": "0.82.2",
    "coreVersion": "10.287",
    "createdTime": 1665428352113,
    "modifiedTime": 1665949120169,
    "lastModifiedBy": "IPeKQhMz2Odi77tR"
  }
}
