{
  "_id": "s3cdpvXKYSHaZqEX",
  "name": "Fox Shape",
  "type": "feat",
  "img": "icons/commodities/treasure/figurine-dog.webp",
  "data": {
    "description": {
      "value": "<em>You can change into a fox in addition to your other forms.</em><br/><br/><b>Prerequisites</b><br/>Cha 13, base attack bonus +3, kitsune.<br/><br/><b>Benefits</b><br/>You can take the form of a fox (Pathfinder RPG Bestiary 3 112) whose appearance is static and cannot be changed each time you assume this form. Your bite attack's damage is reduced to 1d3 points of damage on a hit, but you gain a +10 racial bonus on Disguise checks made to appear as a fox. Changing from kitsune to fox shape is a standard action. This ability otherwise functions as beast shape II, and your ability scores change accordingly.",
      "chat": "",
      "unidentified": ""
    },
    "tags": [
      [
        "PFS"
      ],
      [
        "Racial"
      ],
      [
        "Kitsune"
      ]
    ],
    "activation": {
      "cost": 1,
      "type": ""
    },
    "unchainedAction": {
      "activation": {
        "cost": 1,
        "type": ""
      }
    },
    "duration": {
      "value": null,
      "units": ""
    },
    "target": {
      "value": ""
    },
    "range": {
      "value": null,
      "units": "",
      "maxIncrements": 1,
      "minValue": null,
      "minUnits": ""
    },
    "uses": {
      "value": 0,
      "per": null,
      "autoDeductCharges": true,
      "autoDeductChargesCost": "1",
      "maxFormula": "",
      "max": 0
    },
    "measureTemplate": {
      "type": "",
      "size": "",
      "overrideColor": false,
      "customColor": "",
      "overrideTexture": false,
      "customTexture": ""
    },
    "attackName": "",
    "actionType": null,
    "attackBonus": "",
    "critConfirmBonus": "",
    "damage": {
      "parts": [],
      "critParts": [],
      "nonCritParts": []
    },
    "attackParts": [],
    "formulaicAttacks": {
      "count": {
        "formula": ""
      },
      "bonus": {
        "formula": ""
      },
      "label": null
    },
    "formula": "",
    "ability": {
      "attack": null,
      "damage": null,
      "damageMult": 1,
      "critRange": 20,
      "critMult": 2
    },
    "save": {
      "dc": 0,
      "type": "",
      "description": ""
    },
    "effectNotes": [],
    "attackNotes": [],
    "soundEffect": "",
    "changes": [],
    "changeFlags": {
      "loseDexToAC": false,
      "noEncumbrance": false,
      "mediumArmorFullSpeed": false,
      "heavyArmorFullSpeed": false,
      "noStr": false,
      "noDex": false,
      "oneInt": false,
      "oneWis": false,
      "oneCha": false
    },
    "contextNotes": [],
    "links": {
      "children": [],
      "charges": []
    },
    "tag": "",
    "useCustomTag": false,
    "armorProf": {
      "value": [],
      "custom": ""
    },
    "weaponProf": {
      "value": [],
      "custom": ""
    },
    "flags": {
      "boolean": [],
      "dictionary": []
    },
    "scriptCalls": [],
    "featType": "feat",
    "associations": {
      "classes": []
    },
    "showInQuickbar": false,
    "nonlethal": false,
    "abilityType": "none",
    "crOffset": "",
    "disabled": false,
    "size": "med"
  },
  "effects": [],
  "folder": null,
  "sort": 0,
  "permission": {
    "default": 0,
    "T7ruBbHuMiFYUDxv": 3
  },
  "flags": {}
}
