{
  "_id": "5lQmzt3oPWtrZ1Y7",
  "name": "Inspire Heroics",
  "type": "buff",
  "img": "systems/pf1/icons/skills/emerald_01.jpg",
  "system": {
    "description": {
      "value": "<p>You gain a +4 morale bonus on saving throws and a +4 dodge bonus to AC. The effect lasts for as long as you are able to witness the performance. Inspire heroics is a mind-affecting ability that relies on audible and visual components.</p>",
      "chat": "",
      "unidentified": ""
    },
    "tags": [],
    "changes": [
      {
        "_id": "7qpbs5uj",
        "formula": "4",
        "operator": "add",
        "subTarget": "allSavingThrows",
        "modifier": "morale",
        "priority": 0,
        "value": 0,
        "target": "savingThrows"
      },
      {
        "_id": "5lndyxc1",
        "formula": "4",
        "operator": "add",
        "subTarget": "ac",
        "modifier": "dodge",
        "priority": 0,
        "value": 0,
        "target": "ac"
      }
    ],
    "changeFlags": {
      "loseDexToAC": false,
      "noEncumbrance": false,
      "mediumArmorFullSpeed": false,
      "heavyArmorFullSpeed": false
    },
    "contextNotes": [],
    "links": {
      "children": []
    },
    "tag": "inspireHeroics",
    "useCustomTag": false,
    "flags": {
      "boolean": {},
      "dictionary": {}
    },
    "scriptCalls": [],
    "buffType": "temp",
    "active": false,
    "level": "",
    "duration": {
      "value": null,
      "units": ""
    },
    "hideFromToken": false,
    "uses": {
      "value": 0,
      "max": 0
    },
    "identifiedName": "Inspire Heroics",
    "range": {
      "maxIncrements": 1
    }
  },
  "ownership": {
    "default": 0
  },
  "_stats": {
    "systemId": "pf1",
    "systemVersion": "0.82.5",
    "coreVersion": "10.291",
    "createdTime": 1665428265941,
    "modifiedTime": 1677435308076,
    "lastModifiedBy": "IPeKQhMz2Odi77tR"
  },
  "effects": [],
  "folder": null,
  "sort": 0,
  "flags": {}
}
