{
  "_id": "3xXPm7T6NoikRTds",
  "name": "Firework (banshee ballerina)",
  "type": "consumable",
  "img": "systems/pf1/icons/spells/explosion-magenta-2.jpg",
  "data": {
    "description": {
      "value": "<h1 class=\"title\"><img src=\"https://www.aonprd.com/images/PathfinderSocietySymbol.gif\" style=\"margin:3px 3px 0px 3px;\" title=\"PFS Legal\"/> Firework (banshee ballerina)</h1><b>Source</b> <i>Ultimate Equipment pg. 107</i><br/><b>Price</b> 75 gp; <b>Weight</b> -<br/><b>Category</b> Alchemical Weapons<h2 class=\"framing\">Description</h2><p>This small firework burns brightly and makes a loud, eerie whistling sound. It can be thrown to target an intersection as a splash weapon. Any creatures within 5 feet of the noise are effectively deafened while they remain in the area, as even the loudest sounds they make are drowned out by the piercing sound. A banshee ballerina firework burns for 1d4+1 rounds before extinguishing itself with a quiet puff of smoke. Crafting this item is a DC 30 Craft (alchemy) check.</p><h2 class=\"framing\">Construction</h2><p><b>Craft (Alchemy)</b> DC 30</p>",
      "chat": "",
      "unidentified": ""
    },
    "tags": [],
    "quantity": 1,
    "weight": 0,
    "price": 75,
    "size": "med",
    "equipped": true,
    "resizing": false,
    "identified": true,
    "hp": {
      "max": 10,
      "value": 10
    },
    "broken": false,
    "hardness": 0,
    "carried": true,
    "unidentified": {
      "price": 0,
      "name": ""
    },
    "identifiedName": "",
    "cl": 0,
    "aura": {
      "custom": false,
      "school": ""
    },
    "activation": {
      "cost": 1,
      "type": "standard"
    },
    "unchainedAction": {
      "activation": {
        "cost": 2,
        "type": "action"
      }
    },
    "duration": {
      "value": null,
      "units": ""
    },
    "target": {
      "value": ""
    },
    "range": {
      "value": "10",
      "units": "ft",
      "maxIncrements": "1",
      "minValue": null,
      "minUnits": ""
    },
    "uses": {
      "value": 0,
      "per": null,
      "autoDeductCharges": true,
      "autoDeductChargesCost": "1",
      "maxFormula": "",
      "pricePerUse": 0,
      "max": 0
    },
    "measureTemplate": {
      "type": "",
      "size": "0",
      "overrideColor": false,
      "customColor": "",
      "overrideTexture": false,
      "customTexture": ""
    },
    "attackName": "",
    "actionType": "rsak",
    "attackBonus": "",
    "critConfirmBonus": "",
    "damage": {
      "parts": [
        [
          "",
          "sonic"
        ],
        [
          "",
          ""
        ]
      ],
      "critParts": [],
      "nonCritParts": []
    },
    "attackParts": [],
    "formulaicAttacks": {
      "count": {
        "formula": "",
        "value": 0
      },
      "bonus": {
        "formula": ""
      },
      "label": null
    },
    "formula": "",
    "ability": {
      "attack": "",
      "damage": "",
      "damageMult": 1,
      "critRange": 20,
      "critMult": 1
    },
    "save": {
      "dc": "0",
      "type": "",
      "description": ""
    },
    "effectNotes": [
      "area, see text"
    ],
    "attackNotes": [],
    "soundEffect": "",
    "links": {
      "children": [],
      "charges": []
    },
    "tag": "fireworkBansheeBallerina",
    "useCustomTag": false,
    "flags": {
      "boolean": [],
      "dictionary": [
        [
          "Category",
          "Alchemical Weapons"
        ]
      ]
    },
    "scriptCalls": [],
    "consumableType": "misc",
    "attack": {
      "parts": []
    }
  },
  "effects": [],
  "folder": null,
  "sort": 0,
  "permission": {
    "default": 0,
    "T7ruBbHuMiFYUDxv": 3
  },
  "flags": {}
}
