{
  "_id": "0prLEJ5tLKU50ZsF",
  "name": "Nethys's Dagger",
  "type": "consumable",
  "img": "icons/commodities/flowers/lily-grey-orange.webp",
  "system": {
    "description": {
      "value": "<p><strong>Source</strong> <em>Heroes of the Wild pg. 10</em><br/><strong>Price</strong> 50 gp; <strong>Weight</strong> -<br/><strong>Category</strong> Herbs<br/><strong>Gather</strong> DC 18<br/><strong>Terrain</strong> deserts</p><h2 class=\"framing\">Description</h2><p>Found most often in lands heavily modified by magic, this bulbous cactus is topped with twilight-blue flowers. The sap from the cactus can be used as an additive when crafting potions, causing all variable numeric effects of the potion to be determined as if the potion's caster level were 1 higher. When processed into a powder with a successful DC 15 Craft (alchemy) check, Nethys's dagger can be used as an additional material component when casting spells, granting the user a +1 alchemical bonus on caster level checks to overcome spell resistance.</p>",
      "chat": "",
      "unidentified": ""
    },
    "tags": [],
    "quantity": 1,
    "weight": {
      "value": 0
    },
    "price": 50,
    "size": "med",
    "equipped": true,
    "resizing": false,
    "identified": true,
    "hp": {
      "max": 10,
      "value": 10
    },
    "broken": false,
    "hardness": 0,
    "carried": true,
    "unidentified": {
      "price": 0,
      "name": ""
    },
    "identifiedName": "",
    "cl": 0,
    "aura": {
      "custom": false,
      "school": ""
    },
    "actions": [],
    "uses": {
      "per": null,
      "value": 0,
      "maxFormula": "",
      "pricePerUse": 0,
      "autoDeductCharges": true,
      "autoDeductChargesCost": "1"
    },
    "attackNotes": [],
    "effectNotes": [],
    "links": {
      "children": [],
      "charges": []
    },
    "tag": "nethyssDagger",
    "useCustomTag": false,
    "flags": {
      "boolean": {},
      "dictionary": {
        "Category": "Herbs"
      }
    },
    "scriptCalls": [],
    "consumableType": "misc",
    "showInQuickbar": false,
    "activation": {
      "cost": 1,
      "type": ""
    },
    "unchainedAction": {
      "activation": {
        "cost": 1,
        "type": ""
      }
    },
    "duration": {
      "value": null,
      "units": ""
    },
    "actionType": null,
    "ability": {
      "damageMult": 1,
      "critMult": 2
    },
    "attack": {},
    "range": {
      "maxIncrements": 1
    }
  },
  "effects": [],
  "folder": null,
  "sort": 0,
  "ownership": {
    "default": 0
  },
  "flags": {},
  "_stats": {
    "systemId": "pf1",
    "systemVersion": "0.82.2",
    "coreVersion": "10.287",
    "createdTime": 1665428365700,
    "modifiedTime": 1665949133677,
    "lastModifiedBy": "IPeKQhMz2Odi77tR"
  }
}
